[
    {
        "name": "RoadRunner",
        "alias": "rr",
        "binary": "rr",
        "homepage": "https://roadrunner.dev",
        "description": "High-performance PHP application server, load-balancer and process manager written in Golang",
        "repositories": [
            {
                "type": "github",
                "uri": "roadrunner-server/roadrunner",
                "asset-pattern": "/^roadrunner-.*/"
            }
        ],
        "files": [
            {
                "pattern": "/^(roadrunner|rr)(?:\\.exe)?$/",
                "rename": "rr"
            }
        ]
    },
    {
        "name": "Temporal",
        "alias": "temporal",
        "binary": "temporal",
        "description": "Temporal SDK",
        "homepage": "https://temporal.io",
        "repositories": [
            {
                "type": "github",
                "uri": "temporalio/cli",
                "asset-pattern": "/^temporal_cli_.*/"
            }
        ]
    },
    {
        "name": "Dolt",
        "alias": "dolt",
        "binary": "dolt",
        "description": "Dolt is a SQL database that you can fork, clone, branch, merge, push and pull just like a git repository.",
        "homepage": "https://www.dolthub.com",
        "repositories": [
            {
                "type": "github",
                "uri": "dolthub/dolt",
                "asset-pattern": "/^dolt-.*/"
            }
        ]
    },
    {
        "name": "ProtoC PHP gRPC Plugin",
        "alias": "protoc-gen-php-grpc",
        "binary": "protoc-gen-php-grpc",
        "description": "Protobuf PHP gRPC generator plugin",
        "repositories": [
            {
                "type": "github",
                "uri": "roadrunner-server/roadrunner",
                "asset-pattern": "/^protoc-gen-php-grpc-.*/"
            }
        ]
    },
    {
        "name": "Protobuf compiler",
        "alias": "protoc",
        "binary": "protoc",
        "homepage": "https://protobuf.dev/",
        "repositories": [
            {
                "type": "github",
                "uri": "protocolbuffers/protobuf",
                "asset-pattern": "/^protoc-.*/"
            }
        ]
    },
    {
        "name": "TigerBeetle ",
        "alias": "tigerbeetle",
        "binary": "tigerbeetle",
        "description": "TigerBeetle is a financial transactions database designed for mission critical safety and performance to power the next 30 years of OLTP.",
        "homepage": "https://tigerbeetle.com/",
        "repositories": [
            {
                "type": "github",
                "uri": "tigerbeetle/tigerbeetle",
                "asset-pattern": "/^tigerbeetle-.*/"
            }
        ]
    }
]
